{
  "adult": false,
  "also_known_as": [
    "Tom McKenzie ",
    "Thomasin Harcourt McKenzie"
  ],
  "biography": "Thomasin Harcourt McKenzie (born 26 July 2000) is an actress from New Zealand. After a minor role in The Hobbit: The Battle of Five Armies, she rose to critical prominece with the lead role in Debra Granik's 2018 drama film Leave No Trace. After supporting roles in the 2019 films The King, Jojo Rabbit and True History of the Kelly Gang, as well as the 2021 thriller Old, Edgar Wright's psychological horror film Last Night in Soho established her as one of the industry's lead actresses.",
  "birthday": "2000-07-26",
  "deathday": null,
  "gender": 1,
  "homepage": "https://gcm.co.nz/artists/thomasin-mckenzie",
  "id": 1356758,
  "imdb_id": "nm5057169",
  "known_for_department": "Acting",
  "name": "Thomasin McKenzie",
  "place_of_birth": "Wellington, New Zealand",
  "popularity": 2.0817,
  "profile_path": "/WOpnEFG5Q8LWxP81MtUrskmVox.jpg"
}