{
  "adult": false,
  "also_known_as": [
    "أمير المصري",
    "Amir ElMasry"
  ],
  "biography": "Amir El-Masry (Arabic: أمير المصري) is an Egyptian-British actor. He won a Scottish BAFTA for his performance in the film Limbo (2020). He was nominated for a British Independent Film Award. He was named a 2020 BAFTA Breakthrough Brit and a 2021 Screen International Star of Tomorrow.\n\nEl-Masry debuted in the Egyptian comedy Ramadan Mabrouk Abu El Alamein Hamouda(2008), for which he was awarded Best Movie Debut at the Egyptian Cinema Oscar Festival.\n\nDescription above from the Wikipedia article Amir El-Masry, licensed under CC-BY-SA, full list of contributors on Wikipedia.",
  "birthday": "1990-08-02",
  "deathday": null,
  "gender": 2,
  "homepage": null,
  "id": 1739403,
  "imdb_id": "nm5011084",
  "known_for_department": "Acting",
  "name": "Amir El-Masry",
  "place_of_birth": null,
  "popularity": 1.1178,
  "profile_path": "/naHrnri1hs5mMcvydNIORuM2nQn.jpg"
}