{
  "adult": false,
  "also_known_as": [],
  "biography": "From Wikipedia, the free encyclopedia.  Dana Elcar (born October 10, 1927) was an American television and movie character actor. Although he appeared in about 40 films, his most memorable role was on the 1980s and 1990s television series MacGyver as Peter Thornton, an administrator working for the Phoenix Foundation. Elcar had appeared in the pilot episode of MacGyver as Andy Colson (a completely different character), but was later cast as Peter Thornton, making his first regular appearance in the 11th episode of the first season.\n\nDescription above from the Wikipedia article Dana Elcar, licensed under CC-BY-SA,full list of contributors on Wikipedia.",
  "birthday": "1927-10-10",
  "deathday": null,
  "gender": 2,
  "homepage": null,
  "id": 37712,
  "imdb_id": "nm0253020",
  "known_for_department": "Acting",
  "name": "Dana Elcar",
  "place_of_birth": "Ferndale, Michigan United States",
  "popularity": 1.0976,
  "profile_path": "/iYYbcpWCikPFPvLWCqwKVvNVvrC.jpg"
}