{
  "adult": false,
  "also_known_as": [
    "Wardell Edwin Bond"
  ],
  "biography": "Wardell Edwin Bond (April 9, 1903 – November 5, 1960) was an American film character actor whose rugged appearance and easygoing charm were featured in more than 200 films, as well as in the NBC television series Wagon Train from 1957 to 1961. Among his best-remembered roles are Bert the cop in Frank Capra's It's a Wonderful Life (1946) and Captain Clayton in John Ford's The Searchers (1956).",
  "birthday": "1903-04-09",
  "deathday": "1960-11-05",
  "gender": 2,
  "homepage": null,
  "id": 4303,
  "imdb_id": "nm0000955",
  "known_for_department": "Acting",
  "name": "Ward Bond",
  "place_of_birth": "Benkelman, Nebraska, USA",
  "popularity": 1.2914,
  "profile_path": "/6F8pPEwBHWDpX04R8LkARFejwtC.jpg"
}