{
  "adult": false,
  "also_known_as": [
    "Katharine Juliet Ross",
    "Katherine Ross",
    "کاترین راس"
  ],
  "biography": "Katharine Juliet Ross (born January 29, 1940) is a retired American actress and author. Trained at the San Francisco Workshop, she is perhaps best known for her role as Elaine Robinson in the 1967 film The Graduate, opposite Dustin Hoffman, which won her an Academy Award nomination for Best Supporting Actress, and her role as Etta Place in 1969's Butch Cassidy and the Sundance Kid, opposite Paul Newman and Robert Redford.",
  "birthday": "1940-01-29",
  "deathday": null,
  "gender": 1,
  "homepage": null,
  "id": 9594,
  "imdb_id": "nm0001684",
  "known_for_department": "Acting",
  "name": "Katharine Ross",
  "place_of_birth": " Los Angeles, California, USA",
  "popularity": 1.3189,
  "profile_path": "/uVuemUvCY7UhM3QkTgqH5V3QVIe.jpg"
}